{
    "type":  "vintageimprovements:centrifugation",
    "ingredients":  [
                        {
                            "tag":  "c:dyes/light_blue"
                        },
                        {
                            "tag":  "c:dyes/light_blue"
                        }
                    ],
    "results":  [
                    {
                        "count":  1,
                        "id":  "minecraft:white_dye"
                    },
                    {
                        "count":  1,
                        "id":  "minecraft:blue_dye"
                    }
                ],
    "processing_time":  1000
}

